{
  "nav.home": "Почетна",
  "nav.rides": "Патувања",
  "nav.myRides": "Мои Патувања",
  "nav.profile": "Профил",
  "nav.signIn": "Најави се",
  "nav.signUp": "Регистрирај се",
  "nav.signOut": "Одјави се",
  "home.title": "Сподели го твоето патување, заштеди пари и чувај ја околината",
  "home.subtitle": "Поврзи се со патници кои одат по твојот пат",
  "home.findRide": "Најди Превоз",
  "home.offerRide": "Понуди Превоз",
  "home.howItWorks": "Како Функционира",
  "home.step1": "Креирај профил",
  "home.step2": "Најди или понуди превоз",
  "home.step3": "Патувајте заедно и заштедете",
  "home.benefits": "Придобивки",
  "home.benefit1": "Заштеди пари за патување",
  "home.benefit2": "Намали го јаглеродниот отпечаток",
  "home.benefit3": "Запознај нови луѓе",
  "home.benefit4": "Патувај удобно",
  "footer.about": "За нас",
  "footer.contact": "Контакт",
  "footer.terms": "Услови",
  "footer.privacy": "Приватност",
  "auth.email": "Е-пошта",
  "auth.password": "Лозинка",
  "auth.name": "Целосно име",
  "auth.phone": "Телефонски број",
  "auth.signIn": "Најави се",
  "auth.signUp": "Регистрирај се",
  "auth.noAccount": "Немаш профил?",
  "auth.haveAccount": "Веќе имаш профил?",
  "rides.from": "Од",
  "rides.to": "До",
  "rides.date": "Датум",
  "rides.time": "Време",
  "rides.seats": "Слободни места",
  "rides.price": "Цена",
  "rides.driver": "Возач",
  "rides.vehicle": "Возило",
  "rides.luggage": "Багаж",
  "rides.join": "Приклучи се",
  "rides.create": "Креирај патување",
  "rides.search": "Пребарај патувања",
  "profile.rating": "Оценка",
  "profile.rides": "Завршени патувања",
  "profile.vehicle": "Мое возило",
  "profile.addVehicle": "Додади возило",
  "profile.editProfile": "Уреди профил",
  "chat.send": "Испрати",
  "chat.message": "Порака"
}
